httpd_pyparser/__init__.py
httpd_pyparser/apache.py
httpd_pyparser/apacheparsetab.py
httpd_pyparser/nginx.py
httpd_pyparser/nginxparsetab.py
httpd_pyparser-0.3.dist-info/AUTHORS
httpd_pyparser-0.3.dist-info/COPYING
httpd_pyparser-0.3.dist-info/LICENSE
httpd_pyparser-0.3.dist-info/METADATA
httpd_pyparser-0.3.dist-info/WHEEL
httpd_pyparser-0.3.dist-info/top_level.txt
httpd_pyparser-0.3.dist-info/RECORD
