Metadata-Version: 2.1
Name: httpd-pyparser
Version: 0.3
Summary: HTTP daemons config files parser for Python 3
Home-page: https://github.com/digitalwave/httpd_pyparser
Author: Ervin Hegedus
Author-email: airween@digitalwave.hu
Maintainer: Ervin Hegedus
Maintainer-email: airween@digitalwave.hu
License: AGPLv3
Classifier: Topic :: Text Processing
Requires-Python: >=3
License-File: LICENSE
License-File: COPYING
License-File: AUTHORS
Requires-Dist: ply (>=3.0)
